MANIFEST.in
README.txt
setup.cfg
setup.py
docs/CREDITS.txt
docs/HISTORY.txt
docs/INSTALL.txt
docs/LICENSE.GPL
docs/LICENSE.txt
src/collective/__init__.py
src/collective.facebook.accounts.egg-info/PKG-INFO
src/collective.facebook.accounts.egg-info/SOURCES.txt
src/collective.facebook.accounts.egg-info/dependency_links.txt
src/collective.facebook.accounts.egg-info/entry_points.txt
src/collective.facebook.accounts.egg-info/namespace_packages.txt
src/collective.facebook.accounts.egg-info/not-zip-safe
src/collective.facebook.accounts.egg-info/requires.txt
src/collective.facebook.accounts.egg-info/top_level.txt
src/collective/facebook/__init__.py
src/collective/facebook/accounts/__init__.py
src/collective/facebook/accounts/config.py
src/collective/facebook/accounts/configure.zcml
src/collective/facebook/accounts/setuphandlers.py
src/collective/facebook/accounts/testing.py
src/collective/facebook/accounts/Extensions/Install.py
src/collective/facebook/accounts/Extensions/__init__.py
src/collective/facebook/accounts/browser/__init__.py
src/collective/facebook/accounts/browser/configure.zcml
src/collective/facebook/accounts/browser/controlpanel.py
src/collective/facebook/accounts/browser/interfaces.py
src/collective/facebook/accounts/browser/css/facebook.css
src/collective/facebook/accounts/browser/icons/facebook.png
src/collective/facebook/accounts/browser/icons/remove.png
src/collective/facebook/accounts/browser/js/facebook.js
src/collective/facebook/accounts/browser/templates/facebook-control-panel.pt
src/collective/facebook/accounts/locales/collective.facebook.accounts.pot
src/collective/facebook/accounts/locales/manual.pot
src/collective/facebook/accounts/locales/es/LC_MESSAGES/collective.facebook.accounts.po
src/collective/facebook/accounts/locales/nl/LC_MESSAGES/collective.facebook.accounts.po
src/collective/facebook/accounts/profiles/default/collective.facebook.accounts_various.txt
src/collective/facebook/accounts/profiles/default/controlpanel.xml
src/collective/facebook/accounts/profiles/default/metadata.xml
src/collective/facebook/accounts/profiles/initial/metadata.xml
src/collective/facebook/accounts/profiles/initial/registry.xml
src/collective/facebook/accounts/profiles/uninstall/registry.xml
src/collective/facebook/accounts/tests/__init__.py
src/collective/facebook/accounts/tests/test_controlpanel.py
src/collective/facebook/accounts/tests/test_setup.py