Metadata-Version: 1.0
Name: collective.facebook.accounts
Version: 1.0b4
Summary: This product allows you to associate Facebook accounts with a Plone site using OAuth authentication.
Home-page: https://github.com/collective/collective.facebook.accounts
Author: Franco Pellegrini
Author-email: frapell@gmail.com
License: GPL
Keywords: plone facebook oauth
Platform: UNKNOWN
Classifier: Development Status :: 4 - Beta
Classifier: Environment :: Web Environment
Classifier: Framework :: Plone
Classifier: Framework :: Plone :: 4.1
Classifier: Framework :: Plone :: 4.2
Classifier: Intended Audience :: System Administrators
Classifier: License :: OSI Approved :: GNU General Public License (GPL)
Classifier: Operating System :: OS Independent
Classifier: Programming Language :: JavaScript
Classifier: Programming Language :: Python
Classifier: Programming Language :: Python :: 2.6
Classifier: Programming Language :: Python :: 2.7
Classifier: Topic :: Software Development :: Libraries :: Python Modules
